{
  "ab_users": [
    {
      "email": "ab@portal.com",
      "password": "Abc@123",
      "name": "2nd Institute"
    }
  ],
  "certificateRequests": [
    {
      "id": "REQ001",
      "title": "Master of Tailoring",
      "learnerName": "Kanish Yathra Raj R",
      "learnerId": "Q2TXxvkbPWfZYD08WY0tA4bK4DB3",
      "courseName": "Master of Tailoring",
      "awardingBody": "First Skill University",
      "issuingBody": "National Council of Vocational Training",
      "certificateNumber": "46730068",
      "lastUpdated": "12/2/2025, 9:46:06 PM",
      "status": "Pending"
    },
    {
      "id": "REQ002",
      "title": "Automotive Service Technician",
      "learnerName": "Rohit Verma",
      "learnerId": "NCVET9856321470",
      "courseName": "Automotive Service Technician - Level 4",
      "awardingBody": "First Skill University",
      "issuingBody": "National Council of Vocational Training",
      "certificateNumber": "78451230",
      "lastUpdated": "12/2/2025, 10:15:40 PM",
      "status": "Pending"
    },
    {
      "id": "REQ003",
      "title": "Computer Hardware & Networking",
      "learnerName": "Megha Sinha",
      "learnerId": "NCVET7834211099",
      "courseName": "Computer Hardware Technician - Level 3",
      "awardingBody": "First Skill University",
      "issuingBody": "National Council of Vocational Training",
      "certificateNumber": "98567342",
      "lastUpdated": "12/2/2025, 10:21:12 PM",
      "status": "Pending"
    },
    {
      "id": "REQ004",
      "title": "Beauty Therapist",
      "learnerName": "Priya Sharma",
      "learnerId": "NCVET4521876309",
      "courseName": "Beauty Therapist - Level 4",
      "awardingBody": "First Skill University",
      "issuingBody": "Skill Council for Beauty & Wellness",
      "certificateNumber": "32145678",
      "lastUpdated": "12/2/2025, 11:05:22 PM",
      "status": "Pending"
    },
    {
      "id": "REQ005",
      "title": "Electrician",
      "learnerName": "Amit Kumar",
      "learnerId": "NCVET6789054321",
      "courseName": "Electrician - Level 3",
      "awardingBody": "First Skill University",
      "issuingBody": "Skill Council for Beauty & Wellness",
      "certificateNumber": "87654321",
      "lastUpdated": "12/2/2025, 11:30:00 PM",
      "status": "Pending"
    }
  ]
}
